Metadata-Version: 1.0
Name: udacity-foundation-distributions
Version: 0.1
Summary: Gaussian and Binomial Distributions
Home-page: UNKNOWN
Author: prashant arora
Author-email: prashantarora998@gmail.com
License: UNKNOWN
Platform: UNKNOWN
